aiohttp_dynamic/__init__.py
aiohttp_dynamic/__main__.py
aiohttp_dynamic/middlewares.py
aiohttp_dynamic/routing.py
aiohttp_dynamic-1.3.0.dist-info/LICENSE
aiohttp_dynamic-1.3.0.dist-info/METADATA
aiohttp_dynamic-1.3.0.dist-info/WHEEL
aiohttp_dynamic-1.3.0.dist-info/top_level.txt
aiohttp_dynamic-1.3.0.dist-info/RECORD
