Metadata-Version: 2.1
Name: aiohttp-dynamic
Version: 1.3.0
Summary: aiohttp extension for creating and modifying dynamic routes in runtime
Home-page: https://github.com/bitrate16/aiohttp-dynamic
Download-URL: https://github.com/bitrate16/aiohttp-dynamic/archive/1.2.0.tar.gz
Author: bitrate16
Author-email: bitrate16@gmail.com
License: Apache License 2.0
Keywords: aiohttp,dynamic,routing,mutable,aiohttp-server
Platform: UNKNOWN
Classifier: Development Status :: 4 - Beta
Classifier: Intended Audience :: Developers
Classifier: Topic :: Software Development :: Libraries :: Python Modules
Classifier: License :: OSI Approved :: Apache Software License
Classifier: Programming Language :: Python :: 3.5
Classifier: Programming Language :: Python :: 3.6
Classifier: Programming Language :: Python :: 3.7
Classifier: Programming Language :: Python :: 3.8
Classifier: Programming Language :: Python :: 3.9
Classifier: Programming Language :: Python :: 3.10
Classifier: Programming Language :: Python :: 3.11
License-File: LICENSE
Requires-Dist: aiohttp
Requires-Dist: yarl
